odoo/addons/hr_commission/README.rst
odoo/addons/hr_commission/__init__.py
odoo/addons/hr_commission/__manifest__.py
odoo/addons/hr_commission/i18n/es.po
odoo/addons/hr_commission/i18n/hr_commission.pot
odoo/addons/hr_commission/i18n/pt.po
odoo/addons/hr_commission/i18n/pt_BR.po
odoo/addons/hr_commission/models/__init__.py
odoo/addons/hr_commission/models/hr_employee.py
odoo/addons/hr_commission/models/res_partner.py
odoo/addons/hr_commission/models/sale_commission_settlement.py
odoo/addons/hr_commission/readme/CONTRIBUTORS.rst
odoo/addons/hr_commission/readme/DESCRIPTION.rst
odoo/addons/hr_commission/readme/ROADMAP.rst
odoo/addons/hr_commission/static/description/icon.png
odoo/addons/hr_commission/static/description/icon.svg
odoo/addons/hr_commission/static/description/index.html
odoo/addons/hr_commission/tests/__init__.py
odoo/addons/hr_commission/tests/test_hr_commission.py
odoo/addons/hr_commission/views/res_partner_view.xml
odoo/addons/hr_commission/views/sale_commission_settlement_views.xml
odoo12_addon_hr_commission-12.0.1.1.1.dist-info/METADATA
odoo12_addon_hr_commission-12.0.1.1.1.dist-info/WHEEL
odoo12_addon_hr_commission-12.0.1.1.1.dist-info/top_level.txt
odoo12_addon_hr_commission-12.0.1.1.1.dist-info/RECORD
